yahist/__init__.py
yahist/fit.py
yahist/hist1d.py
yahist/hist2d.py
yahist/utils.py
yahist-1.14.2.dist-info/METADATA
yahist-1.14.2.dist-info/WHEEL
yahist-1.14.2.dist-info/top_level.txt
yahist-1.14.2.dist-info/RECORD
